[
  {
    "beal": "ሉቃስ ወንጌላዊ ፩ዱ እም፸ወ፪ አርድእት፤ ወ፪፻ወ፸ወ፯ እደው ማኅበራኒሁ።",    
    "title": "ዘነግህ",
    "text": "ይኩን ሰላም በኃይልከ፤ \n ወትፍሥሕትከ ውስተ ማኅፈደ ክበዲከ፤ \n በእንተ አኀውየ ወቢጽየ።",
    "wengel": "ሉቃ 10 ÷ 1 - 17",
    "psalm": "መዝ 121 ÷ 7 - ፍፃ",
    "audio": "አርእዩነ ፍኖቶ"
  },
    {
      "title": "ምስባክ",
      "text": "አልቦ ነገር ወአልቦ ነቢብ ዘኢተሰምዐ ቃሎሙ፤ \n ውስተ ኲሉ ምድር ወጽአ ነገሮሙ፤ \n ወእስከ አጽናፈ ዓለም በጽሐ።",
      "wengel": "ሉቃ 1 ÷ 1 - 5",
      "paul": "ቆላስ 4 ÷ 12 - ፍፃ",
      "meliekt": "1 ዮሐ 1 ÷ 4 - ፍፃ",
      "gh": "ግብ ሐዋርያት 1 ÷ 1 - 6",
      "kidase": "ዘሐዋርያት",
      "psalm": "መዝ 18 ÷ 3 - 4",
      "audio": "አርእዩነ ፍኖቶ"
    }
  ]
  