[
    {
      "beal": "አብርሃም ይስሐቅ ወያዕቆብ፤ ወአባ ሰራባን፤ ወሊቃኖስ ዘእም ፱ ቅዱሳን",    
      "title": "ዘነግህ",
      "text": "ፍታሕ ፍትሕየ ወባልሐኒ፤ \n ወበእንተ ቃልከ አሕይወኒ፤ \n ርኁቅ ሕይወት እምኃጥአን።",
      "wengel": "ሉቃስ 13 ÷ 10 - 18",
      "psalm": "መዝ 2 ÷ 1 - 2",
      "audio": "አርእዩነ ፍኖቶ"
    },
    {
      "title": "ምስባክ",
      "text": "በርህ ሠረቀ ለጻድቃን፤ \n ወለርቱዓነ ልብ ትፍሥሕት፤ \n ይትፌሥሑ ጻድቃን በእግዚአብሔር።",
      "wengel": "ማር 12 ÷ 25 - 28",
      "paul": "ገላትያ 3 ÷ 5 - 15 (2 ቆሮ 4 ÷ 1 - 7)",
      "meliekt": "ያዕቆብ 2 ÷ 21 - ፍ፡ም",
      "gh": "ግብ ሐዋርያት 3 ÷ 12 - 17",
      "kidase": "ዘሠለስቱ ምዕት (ግሩም)",
      "psalm": "መዝ 96 ÷ 11 - 12",
      "audio": "አርእዩነ ፍኖቶ"
    }
  ]
  