[
  {
    "title": "ዕዝል",
    "text": "ሐዋዘ ብርሃነ ጸግወነ እግዚኦ ነግሀ ነቂሐነ እምንዋም ንጊሣ ለቤተ ክርስቲያን ኀበ የኃድር ብዕለ ስብሐቲሁ ንስአል ዘእምኀቤሁ ረድኤተ ወሕይወተ ኲሉ ዘጌሠ ወመጽአ ኀቤሃ ኢይፃሙ።"
  },
  {
    "title": "ማኅሌት",
    "text": "ነግሃ ሰላመ ሀበነ በጽባሕ ፍሥሓ ወበጸሎት ነዓል።"
  },
  {
    "title": "ስብሐተ ነግህ",
    "text": "እስመ ዋካ ይእቲ ወብርሃን መድኃኒት ቤተ ክርስቲያን ምስአል ወምስጋድ።"
  },
  {
    "title": "እስመ ለዓለም",
    "house": "ስማዕ",
    "houseShort": "ዕ",
    "text": "ሕንጽት ዉስተ ገዳም ወሡራሬሃ ይትሌዓል እምአድባር ጽሕፍት ውስተ ወንጌል ማኅደረ መለኮት ደብተራ።"
  },
  {
    "title": "ቅንዋት",
    "house": "ስማዕ",
    "houseShort": "ዕ",
    "text": "አርእየኒ ገጸከ ወአስምዐኒ ቃለከ እስመ ቃልከ አዳም ታበርህ በመስቀልከ ዓውደ ጽድቅ ተናገርከ።"
  },
  {
    "title": "አቡን",
    "house": "ሥረዩ",
    "houseShort": "ረዩ",
    "text": "ብርሃነ ሕይወት ዘኢይጸልም ጸግወነ እግዚኦ እምግብርናት ግዕዛነ ወእምጽልመት ብርሃነ እንተ ጸብሐት ንባርከከ ወለከ ንፌኑ ስብሐተ ወአኰቴተ እስመ አልቦ ባዕድ አምላክ ዘእንበሌከ በሰማይ በላዕሉ ወበምድር በታሕቱ መሐሪ እግዚአብሔር መኑ ከማከ።"
  },
  {
    "title": "ሰላም",
    "house": "አንገርጋሪ",
    "houseShort": "ሪ",
    "text": "እነግር ጽድቀከ በዳኅናየ ወትረ እሴብሐከ ወእዜምር ለከ ዘበትእዛዝከ ተሠርዓ ጎሕ ወጽባሕ ኮነ ብርሃነ ወጸብሐ በኲሉ ሰላም ወጥዒና ይረስየነ ነሃሉ።"
  }
]
